murano_tempest_tests/__init__.py
murano_tempest_tests/clients.py
murano_tempest_tests/config.py
murano_tempest_tests/plugin.py
murano_tempest_tests/utils.py
murano_tempest_tests/extras/MockApp/logo.png
murano_tempest_tests/extras/MockApp/Classes/mock_muranopl.yaml
murano_tempest_tests/extras/MockApp/UI/ui.yaml
murano_tempest_tests/extras/io.murano.apps.test.ApacheHttpServerCustom/manifest.yaml
murano_tempest_tests/extras/io.murano.apps.test.ApacheHttpServerCustom/Classes/ApacheHttpServer.yaml
murano_tempest_tests/extras/io.murano.apps.test.ApacheHttpServerCustom/Resources/index.html
murano_tempest_tests/extras/io.murano.apps.test.Lighttpd/manifest.yaml
murano_tempest_tests/extras/io.murano.apps.test.Lighttpd/Classes/Lighttpd.yaml
murano_tempest_tests/extras/io.murano.apps.test.Lighttpd/Resources/DeployLighttpd.template
murano_tempest_tests/extras/io.murano.apps.test.Lighttpd/Resources/scripts/deployLighttpd.sh
murano_tempest_tests/extras/io.murano.apps.test.UpdateExecutor/manifest.yaml
murano_tempest_tests/extras/io.murano.apps.test.UpdateExecutor/Classes/UpdateExecutor.yaml
murano_tempest_tests/extras/io.murano.apps.test.UpdateExecutor/Resources/scripts/update.sh
murano_tempest_tests/extras/io.murano.apps.test.VM/manifest.yaml
murano_tempest_tests/extras/io.murano.apps.test.VM/Classes/VM.yaml
murano_tempest_tests/extras/io.murano.apps.test.VM/Resources/index.html
murano_tempest_tests/services/__init__.py
murano_tempest_tests/services/orchestration_client.py
murano_tempest_tests/services/application_catalog/__init__.py
murano_tempest_tests/services/application_catalog/application_catalog_client.py
murano_tempest_tests/services/artifacts/__init__.py
murano_tempest_tests/services/artifacts/artifacts_client.py
murano_tempest_tests/services/service_broker/__init__.py
murano_tempest_tests/services/service_broker/service_broker_client.py
murano_tempest_tests/tests/__init__.py
murano_tempest_tests/tests/api/__init__.py
murano_tempest_plugin-2.7.0.dist-info/AUTHORS
murano_tempest_plugin-2.7.0.dist-info/LICENSE
murano_tempest_plugin-2.7.0.dist-info/METADATA
murano_tempest_plugin-2.7.0.dist-info/WHEEL
murano_tempest_plugin-2.7.0.dist-info/entry_points.txt
murano_tempest_plugin-2.7.0.dist-info/pbr.json
murano_tempest_plugin-2.7.0.dist-info/top_level.txt
murano_tempest_plugin-2.7.0.dist-info/RECORD
