Metadata-Version: 2.1
Name: murano-tempest-plugin
Version: 2.7.0
Summary: Tempest plugin for the murano project.
Home-page: https://docs.openstack.org/murano/latest/
Author: OpenStack
Author-email: openstack-discuss@lists.openstack.org
License: UNKNOWN
Platform: UNKNOWN
Classifier: Environment :: OpenStack
Classifier: Intended Audience :: Information Technology
Classifier: Intended Audience :: System Administrators
Classifier: License :: OSI Approved :: Apache Software License
Classifier: Operating System :: POSIX :: Linux
Classifier: Programming Language :: Python
Classifier: Programming Language :: Python :: Implementation :: CPython
Classifier: Programming Language :: Python :: 3 :: Only
Classifier: Programming Language :: Python :: 3
Classifier: Programming Language :: Python :: 3.5
Classifier: Programming Language :: Python :: 3.6
Classifier: Programming Language :: Python :: 3.7
Classifier: Programming Language :: Python :: 3.8
Requires-Python: >=3.6
Requires-Dist: oslo.config (>=5.2.0)
Requires-Dist: oslo.serialization (!=2.19.1,>=2.18.0)
Requires-Dist: oslo.utils (>=3.33.0)
Requires-Dist: pbr (!=2.1.0,>=2.0.0)
Requires-Dist: python-heatclient (>=1.10.0)
Requires-Dist: python-keystoneclient (>=3.8.0)
Requires-Dist: python-mistralclient (!=3.2.0,>=3.1.0)
Requires-Dist: python-muranoclient (>=0.8.2)
Requires-Dist: python-neutronclient (>=6.7.0)
Requires-Dist: requests (>=2.14.2)
Requires-Dist: tempest (>=17.1.0)
Requires-Dist: testresources (>=2.0.0)
Requires-Dist: testtools (>=2.2.0)
